poetry_plugin_export_packages/__init__.py
poetry_plugin_export_packages/export_output.py
poetry_plugin_export_packages/plugin.py
poetry_plugin_export_packages-1.0.3.dist-info/LICENSE
poetry_plugin_export_packages-1.0.3.dist-info/METADATA
poetry_plugin_export_packages-1.0.3.dist-info/WHEEL
poetry_plugin_export_packages-1.0.3.dist-info/entry_points.txt
poetry_plugin_export_packages-1.0.3.dist-info/RECORD
