Metadata-Version: 2.1
Name: poetry-plugin-export-packages
Version: 1.0.3
Summary: Poetry plugin to export project dependencies as separate pip packages.
License: MIT
Keywords: poetry,plugin
Author: Ilya O.
Author-email: vrghost@gmail.com
Requires-Python: >=3.8,<4
Classifier: Intended Audience :: Developers
Classifier: License :: OSI Approved :: MIT License
Classifier: Operating System :: OS Independent
Classifier: Programming Language :: Python :: 3
Classifier: Programming Language :: Python :: 3.8
Classifier: Programming Language :: Python :: 3.9
Classifier: Programming Language :: Python :: 3.10
Classifier: Programming Language :: Python :: 3.11
Classifier: Programming Language :: Python :: 3.12
Requires-Dist: poetry (>=1.7.0)
Project-URL: Source, https://github.com/VRGhost/poetry-plugin-export-packages
